<?xml version="1.0" encoding="utf-8" ?>
		<SBCPartOrderRequest>
			<TrackingInfo>
				<TrackNum>110-7169250</TrackNum>
			</TrackingInfo>
			<BuyerInfo>
				<CustomerID>APD1001</CustomerID>
				<Password>9265</Password>
			</BuyerInfo>
			<SellingStore>1</SellingStore>
			<PONum>110-7169250</PONum>
			<CancelOrderFlag>N</CancelOrderFlag>
			<JobNumber>-2489015</JobNumber>
			<UseSellPrice>Y</UseSellPrice>
			<Items>
				<Item>
						<ItemID>1</ItemID>
						<MfgCode>APK</MfgCode>
						<PartNum>J27242</PartNum>
						<Qty>1</Qty>
						<QtyOrder>1</QtyOrder>
						<SellPrice>103.56</SellPrice>
				</Item>
			</Items>
			<SoldTo>
				<CompanyName>VELESTRUMF</CompanyName>
				<Street>501 CRANBROOK</Street>
				<City>LOCKPORT</City>
				<State>IL</State>
				<ZipCode>60333</ZipCode>
				<Phone>6302061166</Phone>
			</SoldTo>
			<ShipTo>
				<CompanyName>karla boucher</CompanyName>
				<LastName></LastName>
				<Street>1016 REDHAWK CT</Street>
				<City>RICHMOND</City>
				<State>ca</State>
				<ZipCode>94806-5842</ZipCode>
				<Phone>510-3947834</Phone>
				<ResidentialDelivery>Y</ResidentialDelivery>
			</ShipTo>
			<ShipVia>F</ShipVia>
		</SBCPartOrderRequest>
		